{
  "teamA": "Al Hilal",
  "teamB": "Istiklol",
  "matches": [
    {
      "matchId": "632220",
      "date": "2022-04-19",
      "homeTeam": "Istiklol",
      "awayTeam": "Al Hilal",
      "scoreHome": 0,
      "scoreAway": 3,
      "competition": null,
      "leagueSlug": "afc.champions"
    },
    {
      "matchId": "632247",
      "date": "2022-04-15",
      "homeTeam": "Al Hilal",
      "awayTeam": "Istiklol",
      "scoreHome": 1,
      "scoreAway": 0,
      "competition": null,
      "leagueSlug": "afc.champions"
    },
    {
      "matchId": "593826",
      "date": "2021-04-24",
      "homeTeam": "Istiklol",
      "awayTeam": "Al Hilal",
      "scoreHome": 4,
      "scoreAway": 1,
      "competition": null,
      "leagueSlug": "afc.champions"
    },
    {
      "matchId": "593848",
      "date": "2021-04-21",
      "homeTeam": "Al Hilal",
      "awayTeam": "Istiklol",
      "scoreHome": 3,
      "scoreAway": 1,
      "competition": null,
      "leagueSlug": "afc.champions"
    }
  ],
  "updatedAt": "2026-06-24T10:06:17.370Z"
}