{
  "teamA": "América de Cali",
  "teamB": "Patriotas",
  "matches": [
    {
      "matchId": "714251",
      "date": "2024-08-04",
      "homeTeam": "Patriotas",
      "awayTeam": "América de Cali",
      "scoreHome": 1,
      "scoreAway": 1,
      "competition": null,
      "leagueSlug": "col.1"
    },
    {
      "matchId": "693619",
      "date": "2024-02-04",
      "homeTeam": "América de Cali",
      "awayTeam": "Patriotas",
      "scoreHome": 1,
      "scoreAway": 0,
      "competition": null,
      "leagueSlug": "col.1"
    },
    {
      "matchId": "626739",
      "date": "2022-09-19",
      "homeTeam": "América de Cali",
      "awayTeam": "Patriotas",
      "scoreHome": 2,
      "scoreAway": 0,
      "competition": null,
      "leagueSlug": "col.1"
    },
    {
      "matchId": "626386",
      "date": "2022-03-23",
      "homeTeam": "Patriotas",
      "awayTeam": "América de Cali",
      "scoreHome": 2,
      "scoreAway": 1,
      "competition": null,
      "leagueSlug": "col.1"
    },
    {
      "matchId": "614109",
      "date": "2021-08-21",
      "homeTeam": "América de Cali",
      "awayTeam": "Patriotas",
      "scoreHome": 0,
      "scoreAway": 0,
      "competition": null,
      "leagueSlug": "col.1"
    },
    {
      "matchId": "592050",
      "date": "2021-03-04",
      "homeTeam": "Patriotas",
      "awayTeam": "América de Cali",
      "scoreHome": 0,
      "scoreAway": 1,
      "competition": null,
      "leagueSlug": "col.1"
    },
    {
      "matchId": "564906",
      "date": "2020-10-11",
      "homeTeam": "América de Cali",
      "awayTeam": "Patriotas",
      "scoreHome": 3,
      "scoreAway": 0,
      "competition": null,
      "leagueSlug": "col.1"
    }
  ],
  "updatedAt": "2026-06-24T09:16:40.745Z"
}