{
  "teamA": "Antigua GFC",
  "teamB": "Nueva Concepcíon",
  "matches": [
    {
      "matchId": "625131",
      "date": "2022-04-02",
      "homeTeam": "Nueva Concepcíon",
      "awayTeam": "Antigua GFC",
      "scoreHome": 0,
      "scoreAway": 3,
      "competition": null,
      "leagueSlug": "gua.1"
    },
    {
      "matchId": "625199",
      "date": "2022-02-03",
      "homeTeam": "Antigua GFC",
      "awayTeam": "Nueva Concepcíon",
      "scoreHome": 4,
      "scoreAway": 0,
      "competition": null,
      "leagueSlug": "gua.1"
    },
    {
      "matchId": "606206",
      "date": "2021-10-24",
      "homeTeam": "Nueva Concepcíon",
      "awayTeam": "Antigua GFC",
      "scoreHome": 1,
      "scoreAway": 0,
      "competition": null,
      "leagueSlug": "gua.1"
    },
    {
      "matchId": "606275",
      "date": "2021-08-15",
      "homeTeam": "Antigua GFC",
      "awayTeam": "Nueva Concepcíon",
      "scoreHome": 4,
      "scoreAway": 0,
      "competition": null,
      "leagueSlug": "gua.1"
    }
  ],
  "updatedAt": "2026-06-24T09:16:09.176Z"
}