{
  "teamA": "Antofagasta",
  "teamB": "Atlético Goianiense",
  "matches": [
    {
      "matchId": "633502",
      "date": "2022-05-18",
      "homeTeam": "Atlético Goianiense",
      "awayTeam": "Antofagasta",
      "scoreHome": 1,
      "scoreAway": 0,
      "competition": null,
      "leagueSlug": "conmebol.sudamericana"
    },
    {
      "matchId": "633535",
      "date": "2022-04-28",
      "homeTeam": "Antofagasta",
      "awayTeam": "Atlético Goianiense",
      "scoreHome": 2,
      "scoreAway": 1,
      "competition": null,
      "leagueSlug": "conmebol.sudamericana"
    }
  ],
  "updatedAt": "2026-06-24T09:16:10.120Z"
}