{
  "teamA": "Baroka FC",
  "teamB": "Black Leopards",
  "matches": [
    {
      "matchId": "757228",
      "date": "2026-02-01",
      "homeTeam": "Black Leopards",
      "awayTeam": "Baroka FC",
      "scoreHome": 1,
      "scoreAway": 1,
      "competition": "South African First Division",
      "leagueSlug": "rsa.2"
    },
    {
      "matchId": "757193",
      "date": "2025-11-29",
      "homeTeam": "Baroka FC",
      "awayTeam": "Black Leopards",
      "scoreHome": 3,
      "scoreAway": 1,
      "competition": "South African First Division",
      "leagueSlug": "rsa.2"
    }
  ],
  "updatedAt": "2026-06-24T05:36:30.267Z"
}