{
  "teamA": "Copiapó",
  "teamB": "Everton CD",
  "matches": [
    {
      "matchId": "696934",
      "date": "2024-10-20",
      "homeTeam": "Copiapó",
      "awayTeam": "Everton CD",
      "scoreHome": 3,
      "scoreAway": 5,
      "competition": null,
      "leagueSlug": "chi.1"
    },
    {
      "matchId": "696817",
      "date": "2024-05-18",
      "homeTeam": "Everton CD",
      "awayTeam": "Copiapó",
      "scoreHome": 1,
      "scoreAway": 0,
      "competition": null,
      "leagueSlug": "chi.1"
    },
    {
      "matchId": "660545",
      "date": "2023-12-09",
      "homeTeam": "Copiapó",
      "awayTeam": "Everton CD",
      "scoreHome": 2,
      "scoreAway": 0,
      "competition": null,
      "leagueSlug": "chi.1"
    },
    {
      "matchId": "660422",
      "date": "2023-05-20",
      "homeTeam": "Everton CD",
      "awayTeam": "Copiapó",
      "scoreHome": 2,
      "scoreAway": 1,
      "competition": null,
      "leagueSlug": "chi.1"
    }
  ],
  "updatedAt": "2026-06-24T09:16:46.213Z"
}