{
  "teamA": "Deportivo Pasto",
  "teamB": "Independiente Santa Fe",
  "matches": [
    {
      "matchId": "401850880",
      "date": "2026-04-24",
      "homeTeam": "Deportivo Pasto",
      "awayTeam": "Independiente Santa Fe",
      "scoreHome": 1,
      "scoreAway": 2,
      "competition": "Colombia Primera A",
      "leagueSlug": "col.1"
    },
    {
      "matchId": "730427",
      "date": "2025-04-05",
      "homeTeam": "Independiente Santa Fe",
      "awayTeam": "Deportivo Pasto",
      "scoreHome": 1,
      "scoreAway": 1,
      "competition": null,
      "leagueSlug": "col.1"
    },
    {
      "matchId": "723928",
      "date": "2024-12-02",
      "homeTeam": "Independiente Santa Fe",
      "awayTeam": "Deportivo Pasto",
      "scoreHome": 1,
      "scoreAway": 2,
      "competition": null,
      "leagueSlug": "col.1"
    },
    {
      "matchId": "723685",
      "date": "2024-11-29",
      "homeTeam": "Deportivo Pasto",
      "awayTeam": "Independiente Santa Fe",
      "scoreHome": 1,
      "scoreAway": 0,
      "competition": null,
      "leagueSlug": "col.1"
    },
    {
      "matchId": "714410",
      "date": "2024-07-17",
      "homeTeam": "Independiente Santa Fe",
      "awayTeam": "Deportivo Pasto",
      "scoreHome": 2,
      "scoreAway": 1,
      "competition": null,
      "leagueSlug": "col.1"
    },
    {
      "matchId": "693592",
      "date": "2024-01-23",
      "homeTeam": "Deportivo Pasto",
      "awayTeam": "Independiente Santa Fe",
      "scoreHome": 0,
      "scoreAway": 1,
      "competition": null,
      "leagueSlug": "col.1"
    },
    {
      "matchId": "662694",
      "date": "2023-08-07",
      "homeTeam": "Deportivo Pasto",
      "awayTeam": "Independiente Santa Fe",
      "scoreHome": 2,
      "scoreAway": 0,
      "competition": null,
      "leagueSlug": "col.1"
    },
    {
      "matchId": "662305",
      "date": "2023-02-15",
      "homeTeam": "Independiente Santa Fe",
      "awayTeam": "Deportivo Pasto",
      "scoreHome": 0,
      "scoreAway": 2,
      "competition": null,
      "leagueSlug": "col.1"
    },
    {
      "matchId": "626745",
      "date": "2022-09-11",
      "homeTeam": "Independiente Santa Fe",
      "awayTeam": "Deportivo Pasto",
      "scoreHome": 2,
      "scoreAway": 1,
      "competition": null,
      "leagueSlug": "col.1"
    },
    {
      "matchId": "626398",
      "date": "2022-03-17",
      "homeTeam": "Deportivo Pasto",
      "awayTeam": "Independiente Santa Fe",
      "scoreHome": 2,
      "scoreAway": 4,
      "competition": null,
      "leagueSlug": "col.1"
    },
    {
      "matchId": "614067",
      "date": "2021-09-19",
      "homeTeam": "Deportivo Pasto",
      "awayTeam": "Independiente Santa Fe",
      "scoreHome": 0,
      "scoreAway": 1,
      "competition": null,
      "leagueSlug": "col.1"
    },
    {
      "matchId": "591963",
      "date": "2021-03-09",
      "homeTeam": "Independiente Santa Fe",
      "awayTeam": "Deportivo Pasto",
      "scoreHome": 2,
      "scoreAway": 2,
      "competition": null,
      "leagueSlug": "col.1"
    },
    {
      "matchId": "588586",
      "date": "2020-11-29",
      "homeTeam": "Independiente Santa Fe",
      "awayTeam": "Deportivo Pasto",
      "scoreHome": 2,
      "scoreAway": 0,
      "competition": null,
      "leagueSlug": "col.1"
    },
    {
      "matchId": "588589",
      "date": "2020-11-23",
      "homeTeam": "Deportivo Pasto",
      "awayTeam": "Independiente Santa Fe",
      "scoreHome": 1,
      "scoreAway": 0,
      "competition": null,
      "leagueSlug": "col.1"
    },
    {
      "matchId": "564863",
      "date": "2020-11-01",
      "homeTeam": "Deportivo Pasto",
      "awayTeam": "Independiente Santa Fe",
      "scoreHome": 1,
      "scoreAway": 1,
      "competition": null,
      "leagueSlug": "col.1"
    }
  ],
  "updatedAt": "2026-06-24T09:16:56.339Z"
}