{
  "teamA": "Itagüí Leones",
  "teamB": "Jaguares de Córdoba",
  "matches": [
    {
      "matchId": "757336",
      "date": "2025-09-05",
      "homeTeam": "Itagüí Leones",
      "awayTeam": "Jaguares de Córdoba",
      "scoreHome": 0,
      "scoreAway": 1,
      "competition": "Colombia Primera B",
      "leagueSlug": "col.2"
    },
    {
      "matchId": "730637",
      "date": "2025-05-05",
      "homeTeam": "Itagüí Leones",
      "awayTeam": "Jaguares de Córdoba",
      "scoreHome": 1,
      "scoreAway": 3,
      "competition": null,
      "leagueSlug": "col.2"
    },
    {
      "matchId": "730596",
      "date": "2025-03-28",
      "homeTeam": "Jaguares de Córdoba",
      "awayTeam": "Itagüí Leones",
      "scoreHome": 2,
      "scoreAway": 0,
      "competition": null,
      "leagueSlug": "col.2"
    }
  ],
  "updatedAt": "2026-06-24T09:16:59.231Z"
}