{
  "teamA": "Club Jaiba Brava",
  "teamB": "Tepatitlán FC",
  "matches": [
    {
      "matchId": "727519",
      "date": "2025-03-30",
      "homeTeam": "Club Jaiba Brava",
      "awayTeam": "Tepatitlán FC",
      "scoreHome": 2,
      "scoreAway": 1,
      "competition": null,
      "leagueSlug": "mex.2"
    },
    {
      "matchId": "715259",
      "date": "2024-10-12",
      "homeTeam": "Tepatitlán FC",
      "awayTeam": "Club Jaiba Brava",
      "scoreHome": 1,
      "scoreAway": 1,
      "competition": null,
      "leagueSlug": "mex.2"
    },
    {
      "matchId": "625486",
      "date": "2022-02-23",
      "homeTeam": "Club Jaiba Brava",
      "awayTeam": "Tepatitlán FC",
      "scoreHome": 3,
      "scoreAway": 1,
      "competition": null,
      "leagueSlug": "mex.2"
    },
    {
      "matchId": "613268",
      "date": "2021-10-28",
      "homeTeam": "Tepatitlán FC",
      "awayTeam": "Club Jaiba Brava",
      "scoreHome": 1,
      "scoreAway": 1,
      "competition": null,
      "leagueSlug": "mex.2"
    },
    {
      "matchId": "602775",
      "date": "2021-05-22",
      "homeTeam": "Tepatitlán FC",
      "awayTeam": "Club Jaiba Brava",
      "scoreHome": 2,
      "scoreAway": 0,
      "competition": null,
      "leagueSlug": "mex.2"
    },
    {
      "matchId": "602776",
      "date": "2021-05-19",
      "homeTeam": "Club Jaiba Brava",
      "awayTeam": "Tepatitlán FC",
      "scoreHome": 2,
      "scoreAway": 0,
      "competition": null,
      "leagueSlug": "mex.2"
    },
    {
      "matchId": "591215",
      "date": "2021-01-31",
      "homeTeam": "Tepatitlán FC",
      "awayTeam": "Club Jaiba Brava",
      "scoreHome": 1,
      "scoreAway": 0,
      "competition": null,
      "leagueSlug": "mex.2"
    },
    {
      "matchId": "577467",
      "date": "2020-08-31",
      "homeTeam": "Club Jaiba Brava",
      "awayTeam": "Tepatitlán FC",
      "scoreHome": 0,
      "scoreAway": 0,
      "competition": null,
      "leagueSlug": "mex.2"
    }
  ],
  "updatedAt": "2026-06-24T09:16:55.903Z"
}