{
  "teamA": "LALA FC",
  "teamB": "UCV FC",
  "matches": [
    {
      "matchId": "616920",
      "date": "2021-10-05",
      "homeTeam": "LALA FC",
      "awayTeam": "UCV FC",
      "scoreHome": 0,
      "scoreAway": 1,
      "competition": null,
      "leagueSlug": "ven.1"
    },
    {
      "matchId": "616980",
      "date": "2021-08-20",
      "homeTeam": "UCV FC",
      "awayTeam": "LALA FC",
      "scoreHome": 1,
      "scoreAway": 0,
      "competition": null,
      "leagueSlug": "ven.1"
    },
    {
      "matchId": "601387",
      "date": "2021-07-01",
      "homeTeam": "LALA FC",
      "awayTeam": "UCV FC",
      "scoreHome": 0,
      "scoreAway": 2,
      "competition": null,
      "leagueSlug": "ven.1"
    },
    {
      "matchId": "601436",
      "date": "2021-05-15",
      "homeTeam": "UCV FC",
      "awayTeam": "LALA FC",
      "scoreHome": 2,
      "scoreAway": 0,
      "competition": null,
      "leagueSlug": "ven.1"
    }
  ],
  "updatedAt": "2026-06-24T09:16:04.243Z"
}