{
  "teamA": "Power Dynamos",
  "teamB": "Pyramids FC",
  "matches": [
    {
      "matchId": "760737",
      "date": "2026-02-14",
      "homeTeam": "Pyramids FC",
      "awayTeam": "Power Dynamos",
      "scoreHome": 3,
      "scoreAway": 1,
      "competition": "CAF Champions League",
      "leagueSlug": "caf.champions"
    },
    {
      "matchId": "760757",
      "date": "2025-11-29",
      "homeTeam": "Power Dynamos",
      "awayTeam": "Pyramids FC",
      "scoreHome": 0,
      "scoreAway": 1,
      "competition": "CAF Champions League",
      "leagueSlug": "caf.champions"
    }
  ],
  "updatedAt": "2026-06-24T05:36:30.446Z"
}