{
  "league": "por.1",
  "updatedAt": 1776697459677,
  "confidence": 0.26,
  "completeness": 0.4444444444444444,
  "sourceAudit": [
    {
      "type": "local_truth_history",
      "label": "history-2025-2026",
      "ok": true
    },
    {
      "type": "existing_artifact",
      "label": "existing-standings-artifact",
      "ok": false
    },
    {
      "type": "validation",
      "label": "low-confidence:0.26",
      "ok": false
    }
  ],
  "phaseSummary": {
    "hasPhaseTables": false,
    "phaseKeys": [
      "regular"
    ]
  },
  "phaseTables": {
    "regular": [
      {
        "position": 1,
        "rank": 1,
        "teamId": null,
        "team": "C.D. Nacional",
        "teamName": "C.D. Nacional",
        "name": "C.D. Nacional",
        "played": 1,
        "wins": 1,
        "draws": 0,
        "losses": 0,
        "goalsFor": 1,
        "goalsAgainst": 0,
        "goalDiff": 1,
        "points": 3,
        "confidence": 0.9
      },
      {
        "position": 2,
        "rank": 2,
        "teamId": null,
        "team": "Vitória de Guimaraes",
        "teamName": "Vitória de Guimaraes",
        "name": "Vitória de Guimaraes",
        "played": 1,
        "wins": 1,
        "draws": 0,
        "losses": 0,
        "goalsFor": 1,
        "goalsAgainst": 0,
        "goalDiff": 1,
        "points": 3,
        "confidence": 0.9
      },
      {
        "position": 3,
        "rank": 3,
        "teamId": null,
        "team": "AVS",
        "teamName": "AVS",
        "name": "AVS",
        "played": 1,
        "wins": 0,
        "draws": 1,
        "losses": 0,
        "goalsFor": 2,
        "goalsAgainst": 2,
        "goalDiff": 0,
        "points": 1,
        "confidence": 0.9
      },
      {
        "position": 4,
        "rank": 4,
        "teamId": null,
        "team": "Rio Ave",
        "teamName": "Rio Ave",
        "name": "Rio Ave",
        "played": 1,
        "wins": 0,
        "draws": 1,
        "losses": 0,
        "goalsFor": 2,
        "goalsAgainst": 2,
        "goalDiff": 0,
        "points": 1,
        "confidence": 0.9
      },
      {
        "position": 5,
        "rank": 5,
        "teamId": null,
        "team": "Casa Pia",
        "teamName": "Casa Pia",
        "name": "Casa Pia",
        "played": 1,
        "wins": 0,
        "draws": 1,
        "losses": 0,
        "goalsFor": 0,
        "goalsAgainst": 0,
        "goalDiff": 0,
        "points": 1,
        "confidence": 0.9
      },
      {
        "position": 6,
        "rank": 6,
        "teamId": null,
        "team": "Santa Clara",
        "teamName": "Santa Clara",
        "name": "Santa Clara",
        "played": 1,
        "wins": 0,
        "draws": 1,
        "losses": 0,
        "goalsFor": 0,
        "goalsAgainst": 0,
        "goalDiff": 0,
        "points": 1,
        "confidence": 0.9
      },
      {
        "position": 7,
        "rank": 7,
        "teamId": null,
        "team": "Alverca",
        "teamName": "Alverca",
        "name": "Alverca",
        "played": 1,
        "wins": 0,
        "draws": 0,
        "losses": 1,
        "goalsFor": 0,
        "goalsAgainst": 1,
        "goalDiff": -1,
        "points": 0,
        "confidence": 0.9
      },
      {
        "position": 8,
        "rank": 8,
        "teamId": null,
        "team": "Gil Vicente",
        "teamName": "Gil Vicente",
        "name": "Gil Vicente",
        "played": 1,
        "wins": 0,
        "draws": 0,
        "losses": 1,
        "goalsFor": 0,
        "goalsAgainst": 1,
        "goalDiff": -1,
        "points": 0,
        "confidence": 0.9
      }
    ]
  },
  "phases": {
    "regular": [
      {
        "position": 1,
        "rank": 1,
        "teamId": null,
        "team": "C.D. Nacional",
        "teamName": "C.D. Nacional",
        "name": "C.D. Nacional",
        "played": 1,
        "wins": 1,
        "draws": 0,
        "losses": 0,
        "goalsFor": 1,
        "goalsAgainst": 0,
        "goalDiff": 1,
        "points": 3,
        "confidence": 0.9
      },
      {
        "position": 2,
        "rank": 2,
        "teamId": null,
        "team": "Vitória de Guimaraes",
        "teamName": "Vitória de Guimaraes",
        "name": "Vitória de Guimaraes",
        "played": 1,
        "wins": 1,
        "draws": 0,
        "losses": 0,
        "goalsFor": 1,
        "goalsAgainst": 0,
        "goalDiff": 1,
        "points": 3,
        "confidence": 0.9
      },
      {
        "position": 3,
        "rank": 3,
        "teamId": null,
        "team": "AVS",
        "teamName": "AVS",
        "name": "AVS",
        "played": 1,
        "wins": 0,
        "draws": 1,
        "losses": 0,
        "goalsFor": 2,
        "goalsAgainst": 2,
        "goalDiff": 0,
        "points": 1,
        "confidence": 0.9
      },
      {
        "position": 4,
        "rank": 4,
        "teamId": null,
        "team": "Rio Ave",
        "teamName": "Rio Ave",
        "name": "Rio Ave",
        "played": 1,
        "wins": 0,
        "draws": 1,
        "losses": 0,
        "goalsFor": 2,
        "goalsAgainst": 2,
        "goalDiff": 0,
        "points": 1,
        "confidence": 0.9
      },
      {
        "position": 5,
        "rank": 5,
        "teamId": null,
        "team": "Casa Pia",
        "teamName": "Casa Pia",
        "name": "Casa Pia",
        "played": 1,
        "wins": 0,
        "draws": 1,
        "losses": 0,
        "goalsFor": 0,
        "goalsAgainst": 0,
        "goalDiff": 0,
        "points": 1,
        "confidence": 0.9
      },
      {
        "position": 6,
        "rank": 6,
        "teamId": null,
        "team": "Santa Clara",
        "teamName": "Santa Clara",
        "name": "Santa Clara",
        "played": 1,
        "wins": 0,
        "draws": 1,
        "losses": 0,
        "goalsFor": 0,
        "goalsAgainst": 0,
        "goalDiff": 0,
        "points": 1,
        "confidence": 0.9
      },
      {
        "position": 7,
        "rank": 7,
        "teamId": null,
        "team": "Alverca",
        "teamName": "Alverca",
        "name": "Alverca",
        "played": 1,
        "wins": 0,
        "draws": 0,
        "losses": 1,
        "goalsFor": 0,
        "goalsAgainst": 1,
        "goalDiff": -1,
        "points": 0,
        "confidence": 0.9
      },
      {
        "position": 8,
        "rank": 8,
        "teamId": null,
        "team": "Gil Vicente",
        "teamName": "Gil Vicente",
        "name": "Gil Vicente",
        "played": 1,
        "wins": 0,
        "draws": 0,
        "losses": 1,
        "goalsFor": 0,
        "goalsAgainst": 1,
        "goalDiff": -1,
        "points": 0,
        "confidence": 0.9
      }
    ]
  },
  "table": []
}