{
  "slug": "fs.argentina.primera-a-women",
  "teams": {
    "Huracan W": [
      {
        "matchId": "x2XmJvPj",
        "date": "2026-06-29T20:00:00.000Z",
        "opp": "San Lorenzo W",
        "ha": "H",
        "gf": 0,
        "ga": 1,
        "res": "L"
      }
    ],
    "San Lorenzo W": [
      {
        "matchId": "x2XmJvPj",
        "date": "2026-06-29T20:00:00.000Z",
        "opp": "Huracan W",
        "ha": "A",
        "gf": 1,
        "ga": 0,
        "res": "W"
      }
    ],
    "San Luis W": [
      {
        "matchId": "Q1x8Sr24",
        "date": "2026-06-28T21:00:00.000Z",
        "opp": "Boca Juniors W",
        "ha": "H",
        "gf": 0,
        "ga": 0,
        "res": "D"
      }
    ],
    "Boca Juniors W": [
      {
        "matchId": "Q1x8Sr24",
        "date": "2026-06-28T21:00:00.000Z",
        "opp": "San Luis W",
        "ha": "A",
        "gf": 0,
        "ga": 0,
        "res": "D"
      }
    ],
    "Union de Santa Fe W": [
      {
        "matchId": "p4h9QMWG",
        "date": "2026-06-28T18:00:00.000Z",
        "opp": "Ferro W",
        "ha": "H",
        "gf": 1,
        "ga": 2,
        "res": "L"
      }
    ],
    "Ferro W": [
      {
        "matchId": "p4h9QMWG",
        "date": "2026-06-28T18:00:00.000Z",
        "opp": "Union de Santa Fe W",
        "ha": "A",
        "gf": 2,
        "ga": 1,
        "res": "W"
      }
    ],
    "Social Atletico Television W": [
      {
        "matchId": "hlv0U4Xi",
        "date": "2026-06-27T14:00:00.000Z",
        "opp": "Lanus W",
        "ha": "H",
        "gf": 0,
        "ga": 2,
        "res": "L"
      }
    ],
    "Lanus W": [
      {
        "matchId": "hlv0U4Xi",
        "date": "2026-06-27T14:00:00.000Z",
        "opp": "Social Atletico Television W",
        "ha": "A",
        "gf": 2,
        "ga": 0,
        "res": "W"
      }
    ],
    "Banfield W": [
      {
        "matchId": "WKGjw0GM",
        "date": "2026-06-27T18:00:00.000Z",
        "opp": "Gimnasia L.P. W",
        "ha": "H",
        "gf": 2,
        "ga": 2,
        "res": "D"
      }
    ],
    "Gimnasia L.P. W": [
      {
        "matchId": "WKGjw0GM",
        "date": "2026-06-27T18:00:00.000Z",
        "opp": "Banfield W",
        "ha": "A",
        "gf": 2,
        "ga": 2,
        "res": "D"
      }
    ],
    "River Plate W": [
      {
        "matchId": "b7IruMoA",
        "date": "2026-06-26T16:00:00.000Z",
        "opp": "Newells Old Boys W",
        "ha": "H",
        "gf": 1,
        "ga": 0,
        "res": "W"
      }
    ],
    "Newells Old Boys W": [
      {
        "matchId": "b7IruMoA",
        "date": "2026-06-26T16:00:00.000Z",
        "opp": "River Plate W",
        "ha": "A",
        "gf": 0,
        "ga": 1,
        "res": "L"
      }
    ],
    "Belgrano W": [
      {
        "matchId": "48PZtrHc",
        "date": "2026-06-26T18:00:00.000Z",
        "opp": "Racing Club W",
        "ha": "H",
        "gf": 0,
        "ga": 0,
        "res": "D"
      }
    ],
    "Racing Club W": [
      {
        "matchId": "48PZtrHc",
        "date": "2026-06-26T18:00:00.000Z",
        "opp": "Belgrano W",
        "ha": "A",
        "gf": 0,
        "ga": 0,
        "res": "D"
      }
    ],
    "Independiente W": [
      {
        "matchId": "hUeHO01T",
        "date": "2026-06-26T18:00:00.000Z",
        "opp": "Talleres Cordoba W",
        "ha": "H",
        "gf": 1,
        "ga": 3,
        "res": "L"
      }
    ],
    "Talleres Cordoba W": [
      {
        "matchId": "hUeHO01T",
        "date": "2026-06-26T18:00:00.000Z",
        "opp": "Independiente W",
        "ha": "A",
        "gf": 3,
        "ga": 1,
        "res": "W"
      }
    ]
  },
  "updatedAt": "2026-07-02T08:15:02.428Z"
}