[
  {
    "matchId": "official-route-nor-2-2026-10-11-17-00-sane-sogndal-127",
    "matchKey": "official-route-nor-2-2026-10-11-17-00-sane-sogndal-127",
    "source": "official_route_fixture_evidence",
    "sourceId": "official_route_norway_fixture_result_table",
    "sourceMatchId": "official-route-nor-2-2026-10-11-17-00-sane-sogndal-127",
    "leagueSlug": "nor.2",
    "leagueName": "",
    "dayKey": "2026-10-11",
    "fetchedDayKey": "2026-10-11",
    "kickoffUtc": "",
    "kickoffLocal": "2026-10-11T17:00",
    "homeTeam": "Åsane",
    "awayTeam": "Sogndal",
    "scoreHome": null,
    "scoreAway": null,
    "penalties": null,
    "decidedBy": null,
    "status": "PRE",
    "rawStatus": "scheduled",
    "minute": null,
    "venue": "",
    "sourceUrl": "https://www.obos-ligaen.no/terminliste",
    "evidence": {
      "sourceType": "official_route_fixture_evidence",
      "sourceContract": "official_route_norway_fixture_result_table",
      "provider": "norway_ntf_official",
      "sourceFamily": "official_route_registry",
      "trustTier": "official_registry_provider_contract",
      "evidenceType": "fixture_or_result",
      "sourcePageKind": "schedule",
      "finalUrl": "https://www.obos-ligaen.no/terminliste",
      "candidateUrl": "https://obos-ligaen.no/terminliste",
      "hostname": "obos-ligaen.no",
      "rawText": "#25 | Åsane - Sogndal | 11.10. 2026 17:00 * #25 Åsane Arena | Billetter",
      "rawCells": [
        "#25",
        "Åsane - Sogndal",
        "11.10. 2026 17:00 * #25 Åsane Arena",
        "Billetter"
      ],
      "tableIndex": 0,
      "rowIndex": 127
    },
    "firstSeenAt": "2026-06-10T16:01:49.648Z",
    "lastSeenAt": "2026-06-10T16:01:49.648Z"
  },
  {
    "matchId": "official-route-nor-2-2026-10-11-17-00-egersund-h-dd-121",
    "matchKey": "official-route-nor-2-2026-10-11-17-00-egersund-h-dd-121",
    "source": "official_route_fixture_evidence",
    "sourceId": "official_route_norway_fixture_result_table",
    "sourceMatchId": "official-route-nor-2-2026-10-11-17-00-egersund-h-dd-121",
    "leagueSlug": "nor.2",
    "leagueName": "",
    "dayKey": "2026-10-11",
    "fetchedDayKey": "2026-10-11",
    "kickoffUtc": "",
    "kickoffLocal": "2026-10-11T17:00",
    "homeTeam": "Egersund",
    "awayTeam": "Hødd",
    "scoreHome": null,
    "scoreAway": null,
    "penalties": null,
    "decidedBy": null,
    "status": "PRE",
    "rawStatus": "scheduled",
    "minute": null,
    "venue": "",
    "sourceUrl": "https://www.obos-ligaen.no/terminliste",
    "evidence": {
      "sourceType": "official_route_fixture_evidence",
      "sourceContract": "official_route_norway_fixture_result_table",
      "provider": "norway_ntf_official",
      "sourceFamily": "official_route_registry",
      "trustTier": "official_registry_provider_contract",
      "evidenceType": "fixture_or_result",
      "sourcePageKind": "schedule",
      "finalUrl": "https://www.obos-ligaen.no/terminliste",
      "candidateUrl": "https://obos-ligaen.no/terminliste",
      "hostname": "obos-ligaen.no",
      "rawText": "#25 | Egersund - Hødd | 11.10. 2026 17:00 * #25 XL-Bygg Sørvest Arena | Billetter",
      "rawCells": [
        "#25",
        "Egersund - Hødd",
        "11.10. 2026 17:00 * #25 XL-Bygg Sørvest Arena",
        "Billetter"
      ],
      "tableIndex": 0,
      "rowIndex": 121
    },
    "firstSeenAt": "2026-06-10T16:01:49.648Z",
    "lastSeenAt": "2026-06-10T16:01:49.648Z"
  },
  {
    "matchId": "official-route-nor-2-2026-10-11-17-00-kongsvinger-ranheim-tf-120",
    "matchKey": "official-route-nor-2-2026-10-11-17-00-kongsvinger-ranheim-tf-120",
    "source": "official_route_fixture_evidence",
    "sourceId": "official_route_norway_fixture_result_table",
    "sourceMatchId": "official-route-nor-2-2026-10-11-17-00-kongsvinger-ranheim-tf-120",
    "leagueSlug": "nor.2",
    "leagueName": "",
    "dayKey": "2026-10-11",
    "fetchedDayKey": "2026-10-11",
    "kickoffUtc": "",
    "kickoffLocal": "2026-10-11T17:00",
    "homeTeam": "Kongsvinger",
    "awayTeam": "Ranheim TF",
    "scoreHome": null,
    "scoreAway": null,
    "penalties": null,
    "decidedBy": null,
    "status": "PRE",
    "rawStatus": "scheduled",
    "minute": null,
    "venue": "",
    "sourceUrl": "https://www.obos-ligaen.no/terminliste",
    "evidence": {
      "sourceType": "official_route_fixture_evidence",
      "sourceContract": "official_route_norway_fixture_result_table",
      "provider": "norway_ntf_official",
      "sourceFamily": "official_route_registry",
      "trustTier": "official_registry_provider_contract",
      "evidenceType": "fixture_or_result",
      "sourcePageKind": "schedule",
      "finalUrl": "https://www.obos-ligaen.no/terminliste",
      "candidateUrl": "https://obos-ligaen.no/terminliste",
      "hostname": "obos-ligaen.no",
      "rawText": "#25 | Kongsvinger - Ranheim TF | 11.10. 2026 17:00 * #25 Gjemselund 1 kunstgress 11er | Billetter",
      "rawCells": [
        "#25",
        "Kongsvinger - Ranheim TF",
        "11.10. 2026 17:00 * #25 Gjemselund 1 kunstgress 11er",
        "Billetter"
      ],
      "tableIndex": 0,
      "rowIndex": 120
    },
    "firstSeenAt": "2026-06-10T16:01:49.648Z",
    "lastSeenAt": "2026-06-10T16:01:49.648Z"
  },
  {
    "matchId": "official-route-nor-2-2026-10-11-17-00-lyn-str-msgodset-124",
    "matchKey": "official-route-nor-2-2026-10-11-17-00-lyn-str-msgodset-124",
    "source": "official_route_fixture_evidence",
    "sourceId": "official_route_norway_fixture_result_table",
    "sourceMatchId": "official-route-nor-2-2026-10-11-17-00-lyn-str-msgodset-124",
    "leagueSlug": "nor.2",
    "leagueName": "",
    "dayKey": "2026-10-11",
    "fetchedDayKey": "2026-10-11",
    "kickoffUtc": "",
    "kickoffLocal": "2026-10-11T17:00",
    "homeTeam": "Lyn",
    "awayTeam": "Strømsgodset",
    "scoreHome": null,
    "scoreAway": null,
    "penalties": null,
    "decidedBy": null,
    "status": "PRE",
    "rawStatus": "scheduled",
    "minute": null,
    "venue": "",
    "sourceUrl": "https://www.obos-ligaen.no/terminliste",
    "evidence": {
      "sourceType": "official_route_fixture_evidence",
      "sourceContract": "official_route_norway_fixture_result_table",
      "provider": "norway_ntf_official",
      "sourceFamily": "official_route_registry",
      "trustTier": "official_registry_provider_contract",
      "evidenceType": "fixture_or_result",
      "sourcePageKind": "schedule",
      "finalUrl": "https://www.obos-ligaen.no/terminliste",
      "candidateUrl": "https://obos-ligaen.no/terminliste",
      "hostname": "obos-ligaen.no",
      "rawText": "#25 | Lyn - Strømsgodset | 11.10. 2026 17:00 * #25 Bislett stadion | Billetter",
      "rawCells": [
        "#25",
        "Lyn - Strømsgodset",
        "11.10. 2026 17:00 * #25 Bislett stadion",
        "Billetter"
      ],
      "tableIndex": 0,
      "rowIndex": 124
    },
    "firstSeenAt": "2026-06-10T16:01:49.648Z",
    "lastSeenAt": "2026-06-10T16:01:49.648Z"
  },
  {
    "matchId": "official-route-nor-2-2026-10-11-17-00-odd-bryne-125",
    "matchKey": "official-route-nor-2-2026-10-11-17-00-odd-bryne-125",
    "source": "official_route_fixture_evidence",
    "sourceId": "official_route_norway_fixture_result_table",
    "sourceMatchId": "official-route-nor-2-2026-10-11-17-00-odd-bryne-125",
    "leagueSlug": "nor.2",
    "leagueName": "",
    "dayKey": "2026-10-11",
    "fetchedDayKey": "2026-10-11",
    "kickoffUtc": "",
    "kickoffLocal": "2026-10-11T17:00",
    "homeTeam": "Odd",
    "awayTeam": "Bryne",
    "scoreHome": null,
    "scoreAway": null,
    "penalties": null,
    "decidedBy": null,
    "status": "PRE",
    "rawStatus": "scheduled",
    "minute": null,
    "venue": "",
    "sourceUrl": "https://www.obos-ligaen.no/terminliste",
    "evidence": {
      "sourceType": "official_route_fixture_evidence",
      "sourceContract": "official_route_norway_fixture_result_table",
      "provider": "norway_ntf_official",
      "sourceFamily": "official_route_registry",
      "trustTier": "official_registry_provider_contract",
      "evidenceType": "fixture_or_result",
      "sourcePageKind": "schedule",
      "finalUrl": "https://www.obos-ligaen.no/terminliste",
      "candidateUrl": "https://obos-ligaen.no/terminliste",
      "hostname": "obos-ligaen.no",
      "rawText": "#25 | Odd - Bryne | 11.10. 2026 17:00 * #25 Skagerak Arena | Billetter",
      "rawCells": [
        "#25",
        "Odd - Bryne",
        "11.10. 2026 17:00 * #25 Skagerak Arena",
        "Billetter"
      ],
      "tableIndex": 0,
      "rowIndex": 125
    },
    "firstSeenAt": "2026-06-10T16:01:49.648Z",
    "lastSeenAt": "2026-06-10T16:01:49.648Z"
  },
  {
    "matchId": "official-route-nor-2-2026-10-11-17-00-raufoss-moss-119",
    "matchKey": "official-route-nor-2-2026-10-11-17-00-raufoss-moss-119",
    "source": "official_route_fixture_evidence",
    "sourceId": "official_route_norway_fixture_result_table",
    "sourceMatchId": "official-route-nor-2-2026-10-11-17-00-raufoss-moss-119",
    "leagueSlug": "nor.2",
    "leagueName": "",
    "dayKey": "2026-10-11",
    "fetchedDayKey": "2026-10-11",
    "kickoffUtc": "",
    "kickoffLocal": "2026-10-11T17:00",
    "homeTeam": "Raufoss",
    "awayTeam": "Moss",
    "scoreHome": null,
    "scoreAway": null,
    "penalties": null,
    "decidedBy": null,
    "status": "PRE",
    "rawStatus": "scheduled",
    "minute": null,
    "venue": "",
    "sourceUrl": "https://www.obos-ligaen.no/terminliste",
    "evidence": {
      "sourceType": "official_route_fixture_evidence",
      "sourceContract": "official_route_norway_fixture_result_table",
      "provider": "norway_ntf_official",
      "sourceFamily": "official_route_registry",
      "trustTier": "official_registry_provider_contract",
      "evidenceType": "fixture_or_result",
      "sourcePageKind": "schedule",
      "finalUrl": "https://www.obos-ligaen.no/terminliste",
      "candidateUrl": "https://obos-ligaen.no/terminliste",
      "hostname": "obos-ligaen.no",
      "rawText": "#25 | Raufoss - Moss | 11.10. 2026 17:00 * #25 NAMMO stadion | Billetter",
      "rawCells": [
        "#25",
        "Raufoss - Moss",
        "11.10. 2026 17:00 * #25 NAMMO stadion",
        "Billetter"
      ],
      "tableIndex": 0,
      "rowIndex": 119
    },
    "firstSeenAt": "2026-06-10T16:01:49.648Z",
    "lastSeenAt": "2026-06-10T16:01:49.648Z"
  },
  {
    "matchId": "official-route-nor-2-2026-10-11-17-00-sandnes-ulf-haugesund-118",
    "matchKey": "official-route-nor-2-2026-10-11-17-00-sandnes-ulf-haugesund-118",
    "source": "official_route_fixture_evidence",
    "sourceId": "official_route_norway_fixture_result_table",
    "sourceMatchId": "official-route-nor-2-2026-10-11-17-00-sandnes-ulf-haugesund-118",
    "leagueSlug": "nor.2",
    "leagueName": "",
    "dayKey": "2026-10-11",
    "fetchedDayKey": "2026-10-11",
    "kickoffUtc": "",
    "kickoffLocal": "2026-10-11T17:00",
    "homeTeam": "Sandnes Ulf",
    "awayTeam": "Haugesund",
    "scoreHome": null,
    "scoreAway": null,
    "penalties": null,
    "decidedBy": null,
    "status": "PRE",
    "rawStatus": "scheduled",
    "minute": null,
    "venue": "",
    "sourceUrl": "https://www.obos-ligaen.no/terminliste",
    "evidence": {
      "sourceType": "official_route_fixture_evidence",
      "sourceContract": "official_route_norway_fixture_result_table",
      "provider": "norway_ntf_official",
      "sourceFamily": "official_route_registry",
      "trustTier": "official_registry_provider_contract",
      "evidenceType": "fixture_or_result",
      "sourcePageKind": "schedule",
      "finalUrl": "https://www.obos-ligaen.no/terminliste",
      "candidateUrl": "https://obos-ligaen.no/terminliste",
      "hostname": "obos-ligaen.no",
      "rawText": "#25 | Sandnes Ulf - Haugesund | 11.10. 2026 17:00 * #25 Øster Hus Arena | Billetter",
      "rawCells": [
        "#25",
        "Sandnes Ulf - Haugesund",
        "11.10. 2026 17:00 * #25 Øster Hus Arena",
        "Billetter"
      ],
      "tableIndex": 0,
      "rowIndex": 118
    },
    "firstSeenAt": "2026-06-10T16:01:49.648Z",
    "lastSeenAt": "2026-06-10T16:01:49.648Z"
  },
  {
    "matchId": "official-route-nor-2-2026-10-11-17-00-stab-k-str-mmen-126",
    "matchKey": "official-route-nor-2-2026-10-11-17-00-stab-k-str-mmen-126",
    "source": "official_route_fixture_evidence",
    "sourceId": "official_route_norway_fixture_result_table",
    "sourceMatchId": "official-route-nor-2-2026-10-11-17-00-stab-k-str-mmen-126",
    "leagueSlug": "nor.2",
    "leagueName": "",
    "dayKey": "2026-10-11",
    "fetchedDayKey": "2026-10-11",
    "kickoffUtc": "",
    "kickoffLocal": "2026-10-11T17:00",
    "homeTeam": "Stabæk",
    "awayTeam": "Strømmen",
    "scoreHome": null,
    "scoreAway": null,
    "penalties": null,
    "decidedBy": null,
    "status": "PRE",
    "rawStatus": "scheduled",
    "minute": null,
    "venue": "",
    "sourceUrl": "https://www.obos-ligaen.no/terminliste",
    "evidence": {
      "sourceType": "official_route_fixture_evidence",
      "sourceContract": "official_route_norway_fixture_result_table",
      "provider": "norway_ntf_official",
      "sourceFamily": "official_route_registry",
      "trustTier": "official_registry_provider_contract",
      "evidenceType": "fixture_or_result",
      "sourcePageKind": "schedule",
      "finalUrl": "https://www.obos-ligaen.no/terminliste",
      "candidateUrl": "https://obos-ligaen.no/terminliste",
      "hostname": "obos-ligaen.no",
      "rawText": "#25 | Stabæk - Strømmen | 11.10. 2026 17:00 * #25 Nye Nadderud stadion | Billetter",
      "rawCells": [
        "#25",
        "Stabæk - Strømmen",
        "11.10. 2026 17:00 * #25 Nye Nadderud stadion",
        "Billetter"
      ],
      "tableIndex": 0,
      "rowIndex": 126
    },
    "firstSeenAt": "2026-06-10T16:01:49.648Z",
    "lastSeenAt": "2026-06-10T16:01:49.648Z"
  }
]
