{
  "ok": true,
  "dayKey": "2026-07-16",
  "generatedAt": "2026-07-15T23:38:59.826Z",
  "manifestGeneratedAt": "2026-07-15T23:38:56.058Z",
  "inputs": [
    {
      "kind": "canonical_fixtures",
      "artifact": "canonical-fixtures/2026-07-16/bol.1.json",
      "at": "2026-07-15T23:11:42.861Z",
      "staleReason": "snapshot_stale_against_canonical",
      "newerThanManifestMs": -1633197
    },
    {
      "kind": "canonical_fixtures",
      "artifact": "canonical-fixtures/2026-07-16/ecu.1.json",
      "at": "2026-07-15T23:11:42.861Z",
      "staleReason": "snapshot_stale_against_canonical",
      "newerThanManifestMs": -1633197
    },
    {
      "kind": "canonical_fixtures",
      "artifact": "canonical-fixtures/2026-07-16/ecu.2.json",
      "at": "2026-07-15T23:11:42.046Z",
      "staleReason": "snapshot_stale_against_canonical",
      "newerThanManifestMs": -1634012
    },
    {
      "kind": "canonical_fixtures",
      "artifact": "canonical-fixtures/2026-07-16/est.2.json",
      "at": "2026-07-15T23:11:18.657Z",
      "staleReason": "snapshot_stale_against_canonical",
      "newerThanManifestMs": -1657401
    },
    {
      "kind": "canonical_fixtures",
      "artifact": "canonical-fixtures/2026-07-16/isl.2.json",
      "at": "2026-07-15T23:11:18.849Z",
      "staleReason": "snapshot_stale_against_canonical",
      "newerThanManifestMs": -1657209
    },
    {
      "kind": "canonical_fixtures",
      "artifact": "canonical-fixtures/2026-07-16/kaz.2.json",
      "at": "2026-07-15T23:11:20.253Z",
      "staleReason": "snapshot_stale_against_canonical",
      "newerThanManifestMs": -1655805
    },
    {
      "kind": "canonical_fixtures",
      "artifact": "canonical-fixtures/2026-07-16/nor.1.json",
      "at": "2026-07-15T23:11:42.862Z",
      "staleReason": "snapshot_stale_against_canonical",
      "newerThanManifestMs": -1633196
    },
    {
      "kind": "canonical_fixtures",
      "artifact": "canonical-fixtures/2026-07-16/uefa.europa.conf.json",
      "at": "2026-07-15T23:11:42.862Z",
      "staleReason": "snapshot_stale_against_canonical",
      "newerThanManifestMs": -1633196
    },
    {
      "kind": "canonical_fixtures",
      "artifact": "canonical-fixtures/2026-07-16/uefa.europa.json",
      "at": "2026-07-15T23:11:42.861Z",
      "staleReason": "snapshot_stale_against_canonical",
      "newerThanManifestMs": -1633197
    },
    {
      "kind": "canonical_fixtures",
      "artifact": "canonical-fixtures/2026-07-16/usa.2.json",
      "at": "2026-07-15T23:11:28.481Z",
      "staleReason": "snapshot_stale_against_canonical",
      "newerThanManifestMs": -1647577
    },
    {
      "kind": "canonical_fixtures",
      "artifact": "canonical-fixtures/2026-07-16/yem.1.json",
      "at": "2026-07-15T23:11:42.593Z",
      "staleReason": "snapshot_stale_against_canonical",
      "newerThanManifestMs": -1633465
    },
    {
      "kind": "coverage_report",
      "artifact": "coverage-reports/2026-07-16.json",
      "at": "2026-07-15T23:11:42.863Z",
      "staleReason": "snapshot_stale_against_coverage_report",
      "newerThanManifestMs": -1633195
    },
    {
      "kind": "coverage_readiness",
      "artifact": "coverage-readiness/2026-07-16.json",
      "at": "2026-07-15T23:25:11.988Z",
      "staleReason": "snapshot_stale_against_coverage_readiness",
      "newerThanManifestMs": -824070
    }
  ],
  "staleInputs": [],
  "derivedArtifacts": [
    {
      "kind": "snapshot_value",
      "artifact": "deploy-snapshots/2026-07-16/value.json",
      "at": 1784158736056,
      "staleReason": "snapshot_value_stale_against_canonical",
      "olderThanLatestCanonicalMs": 1633194
    },
    {
      "kind": "snapshot_value_audit",
      "artifact": "deploy-snapshots/2026-07-16/value-audit.json",
      "at": "2026-07-15T23:38:56.057Z",
      "staleReason": "snapshot_value_audit_stale_against_canonical",
      "olderThanLatestCanonicalMs": 1633195
    },
    {
      "kind": "plan_b_audit",
      "artifact": "value-plans/2026-07-16/plan-b-audit.json",
      "at": "2026-07-15T23:38:56.138Z",
      "staleReason": "plan_b_audit_stale_against_canonical",
      "olderThanLatestCanonicalMs": 1633276
    },
    {
      "kind": "value_plan_comparison",
      "artifact": "value-comparison/2026-07-16.json",
      "at": "2026-07-15T23:38:56.143Z",
      "staleReason": "value_plan_comparison_stale_against_canonical",
      "olderThanLatestCanonicalMs": 1633281
    }
  ],
  "staleDerivedArtifacts": [],
  "skippedInputs": [
    {
      "kind": "expected_matches",
      "artifact": "expected-matches/2026-07-16.json",
      "at": null,
      "staleReason": "snapshot_stale_against_expected_matches",
      "skipped": "artifact_missing_or_no_timestamp"
    }
  ],
  "reasons": []
}
