{
  "dayKey": "2026-07-18",
  "leagueSlug": "arg.2",
  "leagueName": "Argentina Primera Nacional",
  "updatedAt": "2026-07-05T23:16:47.556Z",
  "count": 9,
  "sourceMeta": {
    "acquisitionProvider": "espn",
    "requestedLeagueSlug": "arg.2",
    "requestedDayKey": "2026-07-18",
    "mergedAt": "2026-07-05T23:16:47.556Z"
  },
  "fixtures": [
    {
      "canonicalId": "cid_arg2_nuevachicago_agropecuario_20260718",
      "matchId": "401843988",
      "matchKey": "nuevachicago|agropecuario|1784323800000",
      "source": "espn",
      "sourceId": "401843988",
      "sourceMatchId": "401843988",
      "leagueSlug": "arg.2",
      "leagueName": "Argentina Primera Nacional",
      "dayKey": "2026-07-18",
      "fetchedDayKey": "2026-07-17",
      "kickoffUtc": "2026-07-17T21:30Z",
      "homeTeam": "Nueva Chicago",
      "awayTeam": "Agropecuario",
      "scoreHome": null,
      "scoreAway": null,
      "penalties": null,
      "decidedBy": null,
      "status": "PRE",
      "rawStatus": "STATUS_SCHEDULED",
      "minute": "0'",
      "venue": "República de Mataderos",
      "firstSeenAt": "2026-07-03T18:39:00.140Z",
      "lastSeenAt": "2026-07-05T23:16:47.500Z"
    },
    {
      "canonicalId": "cid_arg2_ferrocarriloeste_colonsantafe_20260718",
      "matchId": "401843986",
      "matchKey": "ferrocarriloeste|colonsantafe|1784327400000",
      "source": "espn",
      "sourceId": "401843986",
      "sourceMatchId": "401843986",
      "leagueSlug": "arg.2",
      "leagueName": "Argentina Primera Nacional",
      "dayKey": "2026-07-18",
      "fetchedDayKey": "2026-07-17",
      "kickoffUtc": "2026-07-17T22:30Z",
      "homeTeam": "Ferro Carril Oeste",
      "awayTeam": "Colón (Santa Fe)",
      "scoreHome": null,
      "scoreAway": null,
      "penalties": null,
      "decidedBy": null,
      "status": "PRE",
      "rawStatus": "STATUS_SCHEDULED",
      "minute": "0'",
      "venue": "Estadio Arquitecto Ricardo Etcheverri",
      "firstSeenAt": "2026-07-03T18:39:00.141Z",
      "lastSeenAt": "2026-07-05T23:16:47.500Z"
    },
    {
      "canonicalId": "cid_arg2_ciudadbolivar_allboys_20260718",
      "matchId": "401843992",
      "matchKey": "ciudadbolivar|allboys|1784329200000",
      "source": "espn",
      "sourceId": "401843992",
      "sourceMatchId": "401843992",
      "leagueSlug": "arg.2",
      "leagueName": "Argentina Primera Nacional",
      "dayKey": "2026-07-18",
      "fetchedDayKey": "2026-07-17",
      "kickoffUtc": "2026-07-17T23:00Z",
      "homeTeam": "Ciudad de Bolívar",
      "awayTeam": "All Boys",
      "scoreHome": null,
      "scoreAway": null,
      "penalties": null,
      "decidedBy": null,
      "status": "PRE",
      "rawStatus": "STATUS_SCHEDULED",
      "minute": "0'",
      "venue": "Estadio Municipal Eva Perón",
      "firstSeenAt": "2026-07-03T18:39:00.201Z",
      "lastSeenAt": "2026-07-05T23:16:47.501Z"
    },
    {
      "canonicalId": "cid_arg2_temperley_atleticorafaela_20260718",
      "matchId": "401843976",
      "matchKey": "temperley|atleticorafaela|1784331000000",
      "source": "espn",
      "sourceId": "401843976",
      "sourceMatchId": "401843976",
      "leagueSlug": "arg.2",
      "leagueName": "Argentina Primera Nacional",
      "dayKey": "2026-07-18",
      "fetchedDayKey": "2026-07-17",
      "kickoffUtc": "2026-07-17T23:30Z",
      "homeTeam": "Temperley",
      "awayTeam": "Atletico Rafaela",
      "scoreHome": null,
      "scoreAway": null,
      "penalties": null,
      "decidedBy": null,
      "status": "PRE",
      "rawStatus": "STATUS_SCHEDULED",
      "minute": "0'",
      "venue": "Alfredo Beranger",
      "firstSeenAt": "2026-07-03T18:39:00.299Z",
      "lastSeenAt": "2026-07-05T23:16:47.501Z"
    },
    {
      "canonicalId": "cid_arg2_mitresantiagodelestero_racingcordoba_20260718",
      "matchId": "401843987",
      "matchKey": "mitresantiagodelestero|racingcordoba|1784332800000",
      "source": "espn",
      "sourceId": "401843987",
      "sourceMatchId": "401843987",
      "leagueSlug": "arg.2",
      "leagueName": "Argentina Primera Nacional",
      "dayKey": "2026-07-18",
      "fetchedDayKey": "2026-07-17",
      "kickoffUtc": "2026-07-18T00:00Z",
      "homeTeam": "Mitre (Santiago del Estero)",
      "awayTeam": "Racing (Córdoba)",
      "scoreHome": null,
      "scoreAway": null,
      "penalties": null,
      "decidedBy": null,
      "status": "PRE",
      "rawStatus": "STATUS_SCHEDULED",
      "minute": "0'",
      "venue": "Estadio Castiglione",
      "firstSeenAt": "2026-07-03T18:39:00.488Z",
      "lastSeenAt": "2026-07-05T23:16:47.501Z"
    },
    {
      "canonicalId": "cid_arg2_colegiales_midland_20260718",
      "matchId": "401843975",
      "matchKey": "colegiales|midland|1784397600000",
      "source": "espn",
      "sourceId": "401843975",
      "sourceMatchId": "401843975",
      "leagueSlug": "arg.2",
      "leagueName": "Argentina Primera Nacional",
      "dayKey": "2026-07-18",
      "fetchedDayKey": "2026-07-18",
      "kickoffUtc": "2026-07-18T18:00Z",
      "homeTeam": "Colegiales",
      "awayTeam": "Midland",
      "scoreHome": null,
      "scoreAway": null,
      "penalties": null,
      "decidedBy": null,
      "status": "PRE",
      "rawStatus": "STATUS_SCHEDULED",
      "minute": "0'",
      "venue": "Estadio Libertarios Unidos",
      "firstSeenAt": "2026-07-03T18:39:00.553Z",
      "lastSeenAt": "2026-07-05T23:16:47.555Z"
    },
    {
      "canonicalId": "cid_arg2_almirantebrown_estudiantesbuenosaires_20260718",
      "matchId": "401843980",
      "matchKey": "almirantebrown|estudiantesbuenosaires|1784397600000",
      "source": "espn",
      "sourceId": "401843980",
      "sourceMatchId": "401843980",
      "leagueSlug": "arg.2",
      "leagueName": "Argentina Primera Nacional",
      "dayKey": "2026-07-18",
      "fetchedDayKey": "2026-07-18",
      "kickoffUtc": "2026-07-18T18:00Z",
      "homeTeam": "Almirante Brown",
      "awayTeam": "Estudiantes (Buenos Aires)",
      "scoreHome": null,
      "scoreAway": null,
      "penalties": null,
      "decidedBy": null,
      "status": "PRE",
      "rawStatus": "STATUS_SCHEDULED",
      "minute": "0'",
      "venue": "Fragata Presidente Sarmiento",
      "firstSeenAt": "2026-07-03T18:39:00.552Z",
      "lastSeenAt": "2026-07-05T23:16:47.555Z"
    },
    {
      "canonicalId": "cid_arg2_acassuso_santelmo_20260718",
      "matchId": "401843982",
      "matchKey": "acassuso|santelmo|1784397600000",
      "source": "espn",
      "sourceId": "401843982",
      "sourceMatchId": "401843982",
      "leagueSlug": "arg.2",
      "leagueName": "Argentina Primera Nacional",
      "dayKey": "2026-07-18",
      "fetchedDayKey": "2026-07-18",
      "kickoffUtc": "2026-07-18T18:00Z",
      "homeTeam": "Acassuso",
      "awayTeam": "San Telmo",
      "scoreHome": null,
      "scoreAway": null,
      "penalties": null,
      "decidedBy": null,
      "status": "PRE",
      "rawStatus": "STATUS_SCHEDULED",
      "minute": "0'",
      "venue": "La Quema",
      "firstSeenAt": "2026-07-03T18:39:00.552Z",
      "lastSeenAt": "2026-07-05T23:16:47.555Z"
    },
    {
      "canonicalId": "cid_arg2_defensoresbelgrano_losandes_20260718",
      "matchId": "401843983",
      "matchKey": "defensoresbelgrano|losandes|1784397600000",
      "source": "espn",
      "sourceId": "401843983",
      "sourceMatchId": "401843983",
      "leagueSlug": "arg.2",
      "leagueName": "Argentina Primera Nacional",
      "dayKey": "2026-07-18",
      "fetchedDayKey": "2026-07-18",
      "kickoffUtc": "2026-07-18T18:00Z",
      "homeTeam": "Defensores de Belgrano",
      "awayTeam": "Los Andes",
      "scoreHome": null,
      "scoreAway": null,
      "penalties": null,
      "decidedBy": null,
      "status": "PRE",
      "rawStatus": "STATUS_SCHEDULED",
      "minute": "0'",
      "venue": "Juan Pasquale",
      "firstSeenAt": "2026-07-03T18:39:00.553Z",
      "lastSeenAt": "2026-07-05T23:16:47.556Z"
    }
  ]
}