{
  "matchId": "cid_fsfijipremierleague_rewa_nadroga_20260719",
  "markets": {},
  "canonicalId": "cid_fsfijipremierleague_rewa_nadroga_20260719",
  "leagueSlug": "fs.fiji.premier-league",
  "competition": "Premier League",
  "home": "Rewa",
  "away": "Nadroga",
  "kickoffUtc": "2026-07-19T02:00:00.000Z",
  "kickoffLocal": null,
  "dayKey": "2026-07-19",
  "updatedAt": "2026-07-19T00:06:26.005Z",
  "openedAt": "2026-07-17T00:10:42.648Z",
  "aiAssessment": {
    "model": {
      "lambdaHome": 2.828,
      "lambdaAway": 1.737,
      "margin": 0.06,
      "formUsed": true,
      "xgUsed": false,
      "homeFormSample": 2,
      "awayFormSample": 2,
      "homeXgSample": 0,
      "awayXgSample": 0,
      "source": "ai_poisson_standings_plus_form"
    },
    "markets": {
      "1X2": {
        "odds": {
          "home": 1.56,
          "draw": 5.5,
          "away": 4.23
        },
        "probs": {
          "home": 0.605,
          "draw": 0.172,
          "away": 0.223
        }
      },
      "DC": {
        "odds": {
          "12": 1.14,
          "1X": 1.21,
          "X2": 2.39
        },
        "probs": {
          "12": 0.828,
          "1X": 0.777,
          "X2": 0.395
        }
      },
      "OU15": {
        "odds": {
          "over": 1,
          "under": 16.24
        },
        "probs": {
          "over": 0.942,
          "under": 0.058
        }
      },
      "OU25": {
        "odds": {
          "over": 1.13,
          "under": 5.67
        },
        "probs": {
          "over": 0.833,
          "under": 0.167
        }
      },
      "OU35": {
        "odds": {
          "over": 1.41,
          "under": 2.85
        },
        "probs": {
          "over": 0.668,
          "under": 0.332
        }
      },
      "BTTS": {
        "odds": {
          "yes": 1.22,
          "no": 4.2
        },
        "probs": {
          "yes": 0.775,
          "no": 0.225
        }
      }
    }
  },
  "source": "flashscore",
  "oddsBook": null,
  "settlement": {
    "scoreHome": 6,
    "scoreAway": 0,
    "settledAt": "2026-07-21T00:03:14.745Z",
    "markets": {
      "1X2": {
        "pick": "home",
        "actual": "home",
        "hit": true
      },
      "OU25": {
        "pick": "over",
        "actual": "over",
        "hit": true
      },
      "BTTS": {
        "pick": "yes",
        "actual": "no",
        "hit": false
      }
    }
  }
}