{
  "matchId": "cid_fsaustralianplnswu20_sutherlandsharksu20_sydneyolympicu20_20260718",
  "markets": {},
  "canonicalId": "cid_fsaustralianplnswu20_sutherlandsharksu20_sydneyolympicu20_20260718",
  "leagueSlug": "fs.australia.npl-nsw-u20",
  "competition": "NPL NSW U20",
  "home": "Sutherland Sharks U20",
  "away": "Sydney Olympic U20",
  "kickoffUtc": "2026-07-18T09:45:00.000Z",
  "kickoffLocal": null,
  "dayKey": "2026-07-18",
  "updatedAt": "2026-07-18T00:02:57.937Z",
  "openedAt": "2026-07-16T00:08:29.620Z",
  "aiAssessment": {
    "model": {
      "lambdaHome": 2.575,
      "lambdaAway": 1.91,
      "margin": 0.06,
      "formUsed": true,
      "xgUsed": false,
      "homeFormSample": 3,
      "awayFormSample": 3,
      "homeXgSample": 0,
      "awayXgSample": 0,
      "source": "ai_poisson_standings_plus_form"
    },
    "markets": {
      "1X2": {
        "odds": {
          "home": 1.79,
          "draw": 5.06,
          "away": 3.29
        },
        "probs": {
          "home": 0.527,
          "draw": 0.186,
          "away": 0.287
        }
      },
      "DC": {
        "odds": {
          "12": 1.16,
          "1X": 1.32,
          "X2": 1.99
        },
        "probs": {
          "12": 0.814,
          "1X": 0.713,
          "X2": 0.473
        }
      },
      "OU15": {
        "odds": {
          "over": 1.01,
          "under": 15.23
        },
        "probs": {
          "over": 0.938,
          "under": 0.062
        }
      },
      "OU25": {
        "odds": {
          "over": 1.14,
          "under": 5.38
        },
        "probs": {
          "over": 0.825,
          "under": 0.175
        }
      },
      "OU35": {
        "odds": {
          "over": 1.44,
          "under": 2.74
        },
        "probs": {
          "over": 0.655,
          "under": 0.345
        }
      },
      "BTTS": {
        "odds": {
          "yes": 1.2,
          "no": 4.43
        },
        "probs": {
          "yes": 0.787,
          "no": 0.213
        }
      }
    }
  },
  "source": "flashscore",
  "oddsBook": null,
  "settlement": {
    "scoreHome": 3,
    "scoreAway": 1,
    "settledAt": "2026-07-20T00:03:58.633Z",
    "markets": {
      "1X2": {
        "pick": "home",
        "actual": "home",
        "hit": true
      },
      "OU25": {
        "pick": "over",
        "actual": "over",
        "hit": true
      },
      "BTTS": {
        "pick": "yes",
        "actual": "yes",
        "hit": true
      }
    }
  }
}